{
    "FILE FORMAT": {
        "Version": "0.11"
    }, 
    "LINE DATA DEFINITION": {
        "NoVO": [
            14, 
            0
        ], 
        "NoEndFadeInLine": [
            19, 
            0
        ], 
        "LineText": [
            3, 
            0
        ], 
        "AudioLineName": [
            4, 
            0
        ], 
        "VOComment": [
            12, 
            0
        ], 
        "NoBegFadeInLine": [
            18, 
            0
        ], 
        "Unskippable": [
            16, 
            0
        ], 
        "Actions": [
            7, 
            0
        ], 
        "Comments": [
            5, 
            0
        ], 
        "RefID": [
            0, 
            0
        ], 
        "ResponseRef": [
            6, 
            0
        ], 
        "Moods": [
            9, 
            0
        ], 
        "ParentRef": [
            1, 
            0
        ], 
        "LocComment": [
            13, 
            0
        ], 
        "VOChange": [
            15, 
            0
        ], 
        "NoSendingStone": [
            17, 
            0
        ], 
        "Conditions": [
            8, 
            0
        ], 
        "ItemsToRemove": [
            11, 
            0
        ], 
        "ItemsToAdd": [
            10, 
            0
        ], 
        "SpeakerTag": [
            2, 
            0
        ]
    }, 
    "CONVERSATION GROUP": [
        [
            {
                "NeedsVO": "True", 
                "EventScripts": {
                    "OnClose": ""
                }, 
                "Name": "Unnamed Conversation", 
                "NoBegFade": "False", 
                "IsFinal": "False", 
                "NoPlayerWarp": "False", 
                "NoMusic": "False", 
                "IsStoryCritical": "True", 
                "IsAmbient": "True", 
                "Defaults": {
                    "Speaker": "ILLYDIA"
                }, 
                "NoEndFade": "False", 
                "ShouldFacePlayer": "False", 
                "NoSendingStone": "False", 
                "ELock": "False"
            }, 
            [
                "LINE_8842884", 
                "<ROOT>", 
                "ILLYDIA", 
                "|Ch1_IntroForest_FoundCave_LINE_8842884|", 
                "", 
                "", 
                [
                    "LINE_2982298", 
                    "LINE_8324169"
                ], 
                [], 
                [
                    {
                        "items": [
                            {
                                "item": {
                                    "FlagState": "true", 
                                    "Flag": "ILLYDIA_IN_PARTY", 
                                    "Quest": "CurrentParty", 
                                    "Type": "Quest"
                                }, 
                                "type": "item"
                            }
                        ], 
                        "connection": "AND", 
                        "type": "group"
                    }
                ], 
                [], 
                [], 
                [], 
                "", 
                "", 
                0, 
                "False", 
                "False", 
                "False", 
                "False", 
                "False"
            ], 
            [
                "LINE_2982298", 
                "LINE_8842884", 
                "BELAMY", 
                "|Ch1_IntroForest_FoundCave_LINE_2982298|", 
                "", 
                "", 
                [
                    "LINE_8324169"
                ], 
                [], 
                [
                    {
                        "items": [
                            {
                                "item": {
                                    "FlagState": "true", 
                                    "Flag": "BELAMY_IN_PARTY", 
                                    "Quest": "CurrentParty", 
                                    "Type": "Quest"
                                }, 
                                "type": "item"
                            }
                        ], 
                        "connection": "AND", 
                        "type": "group"
                    }
                ], 
                [], 
                [], 
                [], 
                "", 
                "", 
                0, 
                "False", 
                "False", 
                "False", 
                "False", 
                "False"
            ], 
            [
                "LINE_8324169", 
                "LINE_2982298", 
                "<SKIP>", 
                "", 
                "", 
                "", 
                [], 
                [], 
                [], 
                [], 
                [], 
                [], 
                "", 
                "", 
                0, 
                "False", 
                "False", 
                "False", 
                "False", 
                "False"
            ], 
            [
                "LINE_6720351", 
                "<ROOT>", 
                "<DEFAULT>", 
                "", 
                "", 
                "", 
                [], 
                [], 
                [], 
                [], 
                [], 
                [], 
                [], 
                "", 
                "", 
                "", 
                false, 
                "False", 
                "False", 
                "False"
            ]
        ]
    ]
}