{
    "CONVERSATION GROUP": [
        [
            {
                "Defaults": {
                    "Speaker": ""
                },
                "ELock": "True",
                "EventScripts": {
                    "OnClose": ""
                },
                "IsAmbient": "True",
                "IsFinal": "False",
                "IsStoryCritical": "False",
                "Name": "Ch2_LuskanGates_Ambient01",
                "NeedsVO": "False",
                "NoBegFade": "False",
                "NoEndFade": "False",
                "NoMusic": "False",
                "NoPlayerWarp": "False",
                "NoSendingStone": "False",
                "ShouldFacePlayer": "False"
            },
            [
                "LINE_0634681",
                "<ROOT>",
                "PEASANTTALKER1",
                "|Ch2_LuskanGates_Ambients_LINE_0634681|",
                "",
                "",
                [],
                [],
                [
                    {
                        "connection": "AND",
                        "items": [
                            {
                                "item": {
                                    "Flag": "C2_ANQ_Guard1",
                                    "FlagState": "false",
                                    "Quest": "C2.1_A_New_Quest",
                                    "Type": "Quest"
                                },
                                "type": "item"
                            }
                        ],
                        "type": "group"
                    }
                ],
                [],
                [],
                [],
                "",
                "",
                0,
                "False",
                "False",
                "False",
                "False",
                "False"
            ]
        ],
        [
            {
                "Defaults": {
                    "Speaker": ""
                },
                "ELock": "True",
                "EventScripts": {
                    "OnClose": ""
                },
                "IsAmbient": "True",
                "IsFinal": "False",
                "IsStoryCritical": "False",
                "Name": "Ch2_LuskanGates_Ambient02",
                "NeedsVO": "False",
                "NoBegFade": "False",
                "NoEndFade": "False",
                "NoMusic": "False",
                "NoPlayerWarp": "False",
                "NoSendingStone": "False",
                "ShouldFacePlayer": "False"
            },
            [
                "LINE_5876115",
                "<ROOT>",
                "PEASANTTALKER2",
                "|Ch2_LuskanGates_Ambients_LINE_5876115|",
                "",
                "",
                [],
                [],
                [
                    {
                        "connection": "AND",
                        "items": [
                            {
                                "item": {
                                    "Flag": "C2_ANQ_Guard1",
                                    "FlagState": "false",
                                    "Quest": "C2.1_A_New_Quest",
                                    "Type": "Quest"
                                },
                                "type": "item"
                            }
                        ],
                        "type": "group"
                    }
                ],
                [],
                [],
                [],
                "",
                "",
                0,
                "False",
                "False",
                "False",
                "False",
                "False"
            ]
        ],
        [
            {
                "Defaults": {
                    "Speaker": ""
                },
                "ELock": "True",
                "EventScripts": {
                    "OnClose": ""
                },
                "IsAmbient": "True",
                "IsFinal": "False",
                "IsStoryCritical": "False",
                "Name": "Ch2_LuskanGates_Ambient03",
                "NeedsVO": "False",
                "NoBegFade": "False",
                "NoEndFade": "False",
                "NoMusic": "False",
                "NoPlayerWarp": "False",
                "NoSendingStone": "False",
                "ShouldFacePlayer": "False"
            },
            [
                "LINE_7362591",
                "<ROOT>",
                "PEASANTTALKER3",
                "|Ch2_LuskanGates_Ambients_LINE_7362591|",
                "",
                "",
                [],
                [],
                [
                    {
                        "connection": "AND",
                        "items": [
                            {
                                "item": {
                                    "Flag": "C2_ANQ_Guard1",
                                    "FlagState": "false",
                                    "Quest": "C2.1_A_New_Quest",
                                    "Type": "Quest"
                                },
                                "type": "item"
                            }
                        ],
                        "type": "group"
                    }
                ],
                [],
                [],
                [],
                "",
                "",
                0,
                "False",
                "False",
                "False",
                "False",
                "False"
            ]
        ],
        [
            {
                "Defaults": {
                    "Speaker": ""
                },
                "ELock": "False",
                "EventScripts": {
                    "OnClose": ""
                },
                "IsAmbient": "True",
                "IsFinal": "False",
                "IsStoryCritical": "False",
                "Name": "Ch2_LuskanGates_GeneralAmb01",
                "NeedsVO": "False",
                "NoBegFade": "False",
                "NoEndFade": "False",
                "NoMusic": "False",
                "NoPlayerWarp": "False",
                "NoSendingStone": "False",
                "ShouldFacePlayer": "False"
            },
            [
                "LINE_0739439",
                "<ROOT>",
                "<DEFAULT>",
                "|Ch2_LuskanGates_Ambients_LINE_0739439|",
                "",
                "",
                [
                    "LINE_9447291"
                ],
                [],
                [],
                [],
                [],
                [],
                "",
                "",
                "",
                "False",
                "False",
                "False",
                "False",
                "False"
            ],
            [
                "LINE_9447291",
                "LINE_0739439",
                "<DEFAULT>",
                "",
                "",
                "",
                [],
                [],
                [],
                [],
                [],
                [],
                "",
                "",
                "",
                "False",
                "False",
                "False",
                "False",
                "False"
            ]
        ],
        [
            {
                "Defaults": {
                    "Speaker": ""
                },
                "ELock": "False",
                "EventScripts": {
                    "OnClose": ""
                },
                "IsAmbient": "True",
                "IsFinal": "False",
                "IsStoryCritical": "False",
                "Name": "Ch2_LuskanGates_GeneralAmb02",
                "NeedsVO": "False",
                "NoBegFade": "False",
                "NoEndFade": "False",
                "NoMusic": "False",
                "NoPlayerWarp": "False",
                "NoSendingStone": "False",
                "ShouldFacePlayer": "False"
            },
            [
                "LINE_3362336",
                "<ROOT>",
                "<DEFAULT>",
                "|Ch2_LuskanGates_Ambients_LINE_3362336|",
                "",
                "",
                [
                    "LINE_2240840"
                ],
                [],
                [],
                [],
                [],
                [],
                "",
                "",
                "",
                "False",
                "False",
                "False",
                "False",
                "False"
            ],
            [
                "LINE_2240840",
                "LINE_3362336",
                "<DEFAULT>",
                "",
                "",
                "",
                [],
                [],
                [],
                [],
                [],
                [],
                "",
                "",
                "",
                "False",
                "False",
                "False",
                "False",
                "False"
            ]
        ],
        [
            {
                "Defaults": {
                    "Speaker": ""
                },
                "ELock": "False",
                "EventScripts": {
                    "OnClose": ""
                },
                "IsAmbient": "True",
                "IsFinal": "False",
                "IsStoryCritical": "False",
                "Name": "Ch2_LuskanGates_GeneralAmb03",
                "NeedsVO": "False",
                "NoBegFade": "False",
                "NoEndFade": "False",
                "NoMusic": "False",
                "NoPlayerWarp": "False",
                "NoSendingStone": "False",
                "ShouldFacePlayer": "False"
            },
            [
                "LINE_7474941",
                "<ROOT>",
                "<DEFAULT>",
                "|Ch2_LuskanGates_Ambients_LINE_7474941|",
                "",
                "",
                [
                    "LINE_5203026"
                ],
                [],
                [],
                [],
                [],
                [],
                "",
                "",
                "",
                "False",
                "False",
                "False",
                "False",
                "False"
            ],
            [
                "LINE_5203026",
                "LINE_7474941",
                "<DEFAULT>",
                "",
                "",
                "",
                [],
                [],
                [],
                [],
                [],
                [],
                "",
                "",
                "",
                "False",
                "False",
                "False",
                "False",
                "False"
            ]
        ],
        [
            {
                "Defaults": {
                    "Speaker": ""
                },
                "ELock": "False",
                "EventScripts": {
                    "OnClose": ""
                },
                "IsAmbient": "True",
                "IsFinal": "False",
                "IsStoryCritical": "False",
                "Name": "Ch2_LuskanGates_GeneralAmb04",
                "NeedsVO": "False",
                "NoBegFade": "False",
                "NoEndFade": "False",
                "NoMusic": "False",
                "NoPlayerWarp": "False",
                "NoSendingStone": "False",
                "ShouldFacePlayer": "False"
            },
            [
                "LINE_8672333",
                "<ROOT>",
                "<DEFAULT>",
                "|Ch2_LuskanGates_Ambients_LINE_8672333|",
                "",
                "",
                [
                    "LINE_1477080"
                ],
                [],
                [],
                [],
                [],
                [],
                "",
                "",
                "",
                "False",
                "False",
                "False",
                "False",
                "False"
            ],
            [
                "LINE_1477080",
                "LINE_8672333",
                "<DEFAULT>",
                "",
                "",
                "",
                [],
                [],
                [],
                [],
                [],
                [],
                "",
                "",
                "",
                "False",
                "False",
                "False",
                "False",
                "False"
            ]
        ],
        [
            {
                "Defaults": {
                    "Speaker": ""
                },
                "ELock": "False",
                "EventScripts": {
                    "OnClose": ""
                },
                "IsAmbient": "True",
                "IsFinal": "False",
                "IsStoryCritical": "False",
                "Name": "Ch2_LuskanGates_GeneralAmb05",
                "NeedsVO": "False",
                "NoBegFade": "False",
                "NoEndFade": "False",
                "NoMusic": "False",
                "NoPlayerWarp": "False",
                "NoSendingStone": "False",
                "ShouldFacePlayer": "False"
            },
            [
                "LINE_4352717",
                "<ROOT>",
                "<DEFAULT>",
                "|Ch2_LuskanGates_Ambients_LINE_4352717|",
                "",
                "",
                [
                    "LINE_1772511"
                ],
                [],
                [],
                [],
                [],
                [],
                "",
                "",
                "",
                "False",
                "False",
                "False",
                "False",
                "False"
            ],
            [
                "LINE_1772511",
                "LINE_4352717",
                "<DEFAULT>",
                "",
                "",
                "",
                [],
                [],
                [],
                [],
                [],
                [],
                "",
                "",
                "",
                "False",
                "False",
                "False",
                "False",
                "False"
            ]
        ],
        [
            {
                "Defaults": {
                    "Speaker": ""
                },
                "ELock": "False",
                "EventScripts": {
                    "OnClose": ""
                },
                "IsAmbient": "True",
                "IsFinal": "False",
                "IsStoryCritical": "False",
                "Name": "Ch2_LuskanGates_GeneralAmb06",
                "NeedsVO": "False",
                "NoBegFade": "False",
                "NoEndFade": "False",
                "NoMusic": "False",
                "NoPlayerWarp": "False",
                "NoSendingStone": "False",
                "ShouldFacePlayer": "False"
            },
            [
                "LINE_7340255",
                "<ROOT>",
                "<DEFAULT>",
                "|Ch2_LuskanGates_Ambients_LINE_7340255|",
                "",
                "",
                [
                    "LINE_7719241"
                ],
                [],
                [],
                [],
                [],
                [],
                "",
                "",
                "",
                "False",
                "False",
                "False",
                "False",
                "False"
            ],
            [
                "LINE_7719241",
                "LINE_7340255",
                "<DEFAULT>",
                "",
                "",
                "",
                [],
                [],
                [],
                [],
                [],
                [],
                "",
                "",
                "",
                "False",
                "False",
                "False",
                "False",
                "False"
            ]
        ],
        [
            {
                "Defaults": {
                    "Speaker": ""
                },
                "ELock": "False",
                "EventScripts": {
                    "OnClose": ""
                },
                "IsAmbient": "True",
                "IsFinal": "False",
                "IsStoryCritical": "False",
                "Name": "Ch2_LuskanGates_GeneralAmb07",
                "NeedsVO": "False",
                "NoBegFade": "False",
                "NoEndFade": "False",
                "NoMusic": "False",
                "NoPlayerWarp": "False",
                "NoSendingStone": "False",
                "ShouldFacePlayer": "False"
            },
            [
                "LINE_2142554",
                "<ROOT>",
                "<DEFAULT>",
                "|Ch2_LuskanGates_Ambients_LINE_2142554|",
                "",
                "",
                [
                    "LINE_5119596"
                ],
                [],
                [],
                [],
                [],
                [],
                "",
                "",
                "",
                "False",
                "False",
                "False",
                "False",
                "False"
            ],
            [
                "LINE_5119596",
                "LINE_2142554",
                "<DEFAULT>",
                "",
                "",
                "",
                [],
                [],
                [],
                [],
                [],
                [],
                "",
                "",
                "",
                "False",
                "False",
                "False",
                "False",
                "False"
            ]
        ],
        [
            {
                "Defaults": {
                    "Speaker": ""
                },
                "ELock": "False",
                "EventScripts": {
                    "OnClose": ""
                },
                "IsAmbient": "True",
                "IsFinal": "False",
                "IsStoryCritical": "False",
                "Name": "Ch2_LuskanGates_GeneralAmb08",
                "NeedsVO": "False",
                "NoBegFade": "False",
                "NoEndFade": "False",
                "NoMusic": "False",
                "NoPlayerWarp": "False",
                "NoSendingStone": "False",
                "ShouldFacePlayer": "False"
            },
            [
                "LINE_7525248",
                "<ROOT>",
                "<DEFAULT>",
                "|Ch2_LuskanGates_Ambients_LINE_7525248|",
                "",
                "",
                [
                    "LINE_2479945"
                ],
                [],
                [],
                [],
                [],
                [],
                "",
                "",
                "",
                "False",
                "False",
                "False",
                "False",
                "False"
            ],
            [
                "LINE_2479945",
                "LINE_7525248",
                "<DEFAULT>",
                "",
                "",
                "",
                [],
                [],
                [],
                [],
                [],
                [],
                "",
                "",
                "",
                "False",
                "False",
                "False",
                "False",
                "False"
            ]
        ],
        [
            {
                "Defaults": {
                    "Speaker": ""
                },
                "ELock": "False",
                "EventScripts": {
                    "OnClose": ""
                },
                "IsAmbient": "True",
                "IsFinal": "False",
                "IsStoryCritical": "False",
                "Name": "Ch2_LuskanGates_GeneralAmb09",
                "NeedsVO": "False",
                "NoBegFade": "False",
                "NoEndFade": "False",
                "NoMusic": "False",
                "NoPlayerWarp": "False",
                "NoSendingStone": "False",
                "ShouldFacePlayer": "False"
            },
            [
                "LINE_0143146",
                "<ROOT>",
                "<DEFAULT>",
                "|Ch2_LuskanGates_Ambients_LINE_0143146|",
                "",
                "",
                [
                    "LINE_0510724"
                ],
                [],
                [],
                [],
                [],
                [],
                "",
                "",
                "",
                "True",
                "False",
                "False",
                "False",
                "False"
            ],
            [
                "LINE_0510724",
                "LINE_0143146",
                "<DEFAULT>",
                "",
                "",
                "",
                [],
                [],
                [],
                [],
                [],
                [],
                "",
                "",
                "",
                "False",
                "False",
                "False",
                "False",
                "False"
            ]
        ]
    ],
    "FILE FORMAT": {
        "Version": "0.11"
    },
    "LINE DATA DEFINITION": {
        "Actions": [
            7,
            0
        ],
        "AudioLineName": [
            4,
            0
        ],
        "Comments": [
            5,
            0
        ],
        "Conditions": [
            8,
            0
        ],
        "ItemsToAdd": [
            10,
            0
        ],
        "ItemsToRemove": [
            11,
            0
        ],
        "LineText": [
            3,
            0
        ],
        "LocComment": [
            13,
            0
        ],
        "Moods": [
            9,
            0
        ],
        "NoBegFadeInLine": [
            18,
            0
        ],
        "NoEndFadeInLine": [
            19,
            0
        ],
        "NoSendingStone": [
            17,
            0
        ],
        "NoVO": [
            14,
            0
        ],
        "ParentRef": [
            1,
            0
        ],
        "RefID": [
            0,
            0
        ],
        "ResponseRef": [
            6,
            0
        ],
        "SpeakerTag": [
            2,
            0
        ],
        "Unskippable": [
            16,
            0
        ],
        "VOChange": [
            15,
            0
        ],
        "VOComment": [
            12,
            0
        ]
    }
}
